setup.py
dsnd_probability_carlos_benitez/Binomialdistribution_challenge.py
dsnd_probability_carlos_benitez/setup.py
dsnd_probability_carlos_benitez/test.py
dsnd_probability_carlos_benitez.egg-info/PKG-INFO
dsnd_probability_carlos_benitez.egg-info/SOURCES.txt
dsnd_probability_carlos_benitez.egg-info/dependency_links.txt
dsnd_probability_carlos_benitez.egg-info/top_level.txt