Metadata-Version: 1.0
Name: dsnd-probability-carlos-benitez
Version: 1.2
Summary: Gaussian an Binomial distributions
Home-page: UNKNOWN
Author: Carlos Benitez
Author-email: carlitos.benitez@yahoo.com
License: UNKNOWN
Platform: UNKNOWN
